sinapsis_deepseek_ocr/__init__.py
sinapsis_deepseek_ocr/helpers/__init__.py
sinapsis_deepseek_ocr/helpers/bbox_utils.py
sinapsis_deepseek_ocr/helpers/grounding_parser.py
sinapsis_deepseek_ocr/helpers/mode_registry.py
sinapsis_deepseek_ocr/helpers/schemas.py
sinapsis_deepseek_ocr/helpers/tags.py
sinapsis_deepseek_ocr/templates/__init__.py
sinapsis_deepseek_ocr/templates/deepseek_ocr_inference.py
sinapsis_deepseek_ocr-0.1.0.dist-info/licenses/LICENSE
sinapsis_deepseek_ocr-0.1.0.dist-info/METADATA
sinapsis_deepseek_ocr-0.1.0.dist-info/WHEEL
sinapsis_deepseek_ocr-0.1.0.dist-info/top_level.txt
sinapsis_deepseek_ocr-0.1.0.dist-info/RECORD
