Metadata-Version: 2.4
Name: sinapsis-deepseek-ocr
Version: 0.1.0
Summary: A powerful DeepSeek-based Optical Character Recognition (OCR) implementation supporting text extraction and grounding.
Author-email: SinapsisAI <dev@sinapsis.tech>
Project-URL: Homepage, https://sinapsis.tech
Project-URL: Documentation, https://docs.sinapsis.tech/docs
Project-URL: Tutorials, https://docs.sinapsis.tech/tutorials
Project-URL: Repository, https://github.com/Sinapsis-AI/sinapsis-ocr.git
Requires-Python: >=3.10
License-File: LICENSE
Requires-Dist: sinapsis>=0.2.24
Requires-Dist: flash-attn>=2.8.3
Requires-Dist: torch==2.8.0
Requires-Dist: transformers==4.46.3
Requires-Dist: tokenizers==0.20.3
Requires-Dist: einops>=0.8.1
Requires-Dist: addict>=2.4.0
Requires-Dist: easydict>=1.13
Requires-Dist: accelerate>=1.12.0
Requires-Dist: sinapsis-generic-data-tools>=0.1.11
Provides-Extra: sinapsis-data-readers
Requires-Dist: sinapsis-data-readers[opencv]>=0.1.0; extra == "sinapsis-data-readers"
Provides-Extra: sinapsis-data-writers
Requires-Dist: sinapsis-data-writers>=0.1.0; extra == "sinapsis-data-writers"
Provides-Extra: sinapsis-data-visualization
Requires-Dist: sinapsis-data-visualization[visualization-matplotlib]>=0.1.0; extra == "sinapsis-data-visualization"
Provides-Extra: all
Requires-Dist: sinapsis-deepseek-ocr[sinapsis-data-readers]; extra == "all"
Requires-Dist: sinapsis-deepseek-ocr[sinapsis-data-writers]; extra == "all"
Requires-Dist: sinapsis-deepseek-ocr[sinapsis-data-visualization]; extra == "all"
Dynamic: license-file
